py_unsure/__init__.py
py_unsure/core.py
unsurepy/__init__.py
unsurepy/core.py
unsurepy-1.0.2.dist-info/METADATA
unsurepy-1.0.2.dist-info/WHEEL
unsurepy-1.0.2.dist-info/top_level.txt
unsurepy-1.0.2.dist-info/RECORD
