Metadata-Version: 2.1
Name: unsurepy
Version: 1.0.2
Summary: A utility package that leverages the capabilities of llms to allow working with values with undertermined format
Home-page: https://github.com/MeddahAbdellah/py-unsure
Author: Meddah Abdallah
Author-email: meddah.abdellah.spcx@gmail.com
Classifier: Programming Language :: Python :: 3
Classifier: License :: OSI Approved :: MIT License
Classifier: Operating System :: OS Independent
Requires-Python: >=3.7
Requires-Dist: requests
